{"inkVersion":20,"root":[[{"->":"main"},["done",{"#f":5,"#n":"g-0"}],null],"done",{"main":[["^Good day! I am Encarnacion Alzona, but you can call me Elly. I am currently here to learn about our own history. In my free time, I also love visiting bird sanctuaries because I really love birds!","\n","ev","str","^Next","/str","/ev",{"*":".^.c-0","flg":4},{"c-0":["\n","^That's cool. How many bird pets do you have? ",{"#":"You"},"\n",["ev","str","^Next","/str","/ev",{"*":".^.c-0","flg":4},{"c-0":["\n","^I have 12 birds and some of them are rescued.","\n",["ev","str","^Next","/str","/ev",{"*":".^.c-0","flg":4},{"c-0":["\n","^That's a lot. By the way, what program are you taking now? ",{"#":"You"},"\n",["ev","str","^Next","/str","/ev",{"*":".^.c-0","flg":4},{"c-0":["\n","^I am taking Bachelor of Science in Philosophy and History.","\n",["ev","str","^Next","/str","/ev",{"*":".^.c-0","flg":4},{"c-0":["\n","^That's great, Maybe I can ask you questions about the History of our country ",{"#":"You"},"\n",["ev","str","^Next","/str","/ev",{"*":".^.c-0","flg":4},{"c-0":["\n","^Sure! No problem. Just let me know if you think I can help you to know something.","\n",["ev","str","^Next","/str","/ev",{"*":".^.c-0","flg":4},{"c-0":["\n","^Thank you so much! ",{"#":"You"},"\n",["ev","str","^Exit","/str","/ev",{"*":".^.c-0","flg":4},{"c-0":["\n","end",{"#f":5}]}],{"#f":5}]}],{"#f":5}]}],{"#f":5}]}],{"#f":5}]}],{"#f":5}]}],{"#f":5}]}],{"#f":5}]}],{"#f":1}],"#f":1}],"listDefs":{}}