{"inkVersion":20,"root":[[{"->":"main"},["done",{"#f":5,"#n":"g-0"}],null],"done",{"main":[["^Boracay is a  resort island in the Western Visayas region of the Philippines and was was originally inhabited by the Ati people, but commercial development has led to leave and relocate.","\n","ev","str","^Next","/str","/ev",{"*":".^.c-0","flg":4},{"c-0":["\n","^Apart from its white sand beaches, Boracay is also famous for being one of the world's top destinations for relaxation. The island's indigenous Ati people say that the name of the island came from the Inati words \"bora\", meaning bubbles, and \"bocay\", meaning white.","\n",["ev","str","^Next","/str","/ev",{"*":".^.c-0","flg":4},{"c-0":["\n","end",{"#f":5}]}],{"#f":5}]}],{"#f":1}],"#f":1}],"listDefs":{}}