{"inkVersion":20,"root":[[{"->":"main"},["done",{"#f":5,"#n":"g-0"}],null],"done",{"main":[["^The <b>Philippine Eagle</b> is also known as the monkey eating eagle or great Philippine Eagle or in the local language it is called <b>Haribon</b> and is declared as the <b>National Bird of the Philippines</b>, with that, the Philippine Eagle Center wherein located to Davao City, is a center that is home of <b>40 Philippine Eagles</b>.","\n","ev","str","^next","/str","/ev",{"*":".^.c-0","flg":4},{"c-0":["\n","^The center simulates a tropical rainforest similar to what their natural habitat looks and feels like.","\n",["ev","str","^next","/str","/ev",{"*":".^.c-0","flg":4},{"c-0":["\n","end",{"#f":5}]}],{"#f":5}]}],{"#f":1}],"#f":1}],"listDefs":{}}